biocontext_server/__init__.py
biocontext_server/app.py
biocontext_server/logging.py
biocontext_server/main.py
biocontext_server/py.typed
biocontext_server/core/__init__.py
biocontext_server/core/_server.py
biocontext_server/core/alphafold/__init__.py
biocontext_server/core/alphafold/_get_alphafold_info_by_protein_symbol.py
biocontext_server/core/alphafold/_get_alphafold_info_by_uniprot_id.py
biocontext_server/core/alphafold/_get_uniprot_id_by_protein_symbol.py
biocontext_server/core/antibodyregistry/__init__.py
biocontext_server/core/antibodyregistry/_get_antibody_information.py
biocontext_server/core/antibodyregistry/_get_antibody_list.py
biocontext_server/core/biorxiv/__init__.py
biocontext_server/core/biorxiv/_get_preprint_details.py
biocontext_server/core/biorxiv/_get_recent_biorxiv_preprints.py
biocontext_server/core/clinicaltrials/__init__.py
biocontext_server/core/clinicaltrials/_get_recruiting_studies_by_location.py
biocontext_server/core/clinicaltrials/_get_studies_by_condition.py
biocontext_server/core/clinicaltrials/_get_studies_by_intervention.py
biocontext_server/core/clinicaltrials/_get_study_details.py
biocontext_server/core/clinicaltrials/_search_studies.py
biocontext_server/core/ensembl/__init__.py
biocontext_server/core/ensembl/_get_ensembl_id_from_gene_symbol.py
biocontext_server/core/europepmc/__init__.py
biocontext_server/core/europepmc/_get_europepmc_articles.py
biocontext_server/core/europepmc/_get_europepmc_fulltext.py
biocontext_server/core/grants/__init__.py
biocontext_server/core/grants/_search_grants_gov.py
biocontext_server/core/interpro/__init__.py
biocontext_server/core/interpro/_get_interpro_entry.py
biocontext_server/core/interpro/_get_protein_domains.py
biocontext_server/core/interpro/_search_interpro_entries.py
biocontext_server/core/kegg/__init__.py
biocontext_server/core/kegg/_execute_kegg_query.py
biocontext_server/core/kegg/_get_kegg_id_by_gene_symbol.py
biocontext_server/core/kegg/_query_kegg.py
biocontext_server-0.2.4.dist-info/METADATA
biocontext_server-0.2.4.dist-info/WHEEL
biocontext_server-0.2.4.dist-info/entry_points.txt
biocontext_server-0.2.4.dist-info/licenses/LICENSE
biocontext_server-0.2.4.dist-info/RECORD
